{
  "collection_id": 257292,
  "document_id": 3205963,
  "page_id": 74725282,
  "library_identifier": "20129484v4n2",
  "page_number": "003",
  "regions": [
    {
      "region_id": "r",
      "type": "keyword",
      "text": [
        "dansen :\n"
      ]
    },
    {
      "region_id": "r_3",
      "type": "keyword",
      "text": [
        "cister :\n"
      ]
    },
    {
      "region_id": "r_5",
      "type": "keyword",
      "text": [
        "viool :\n"
      ]
    },
    {
      "region_id": "r_7",
      "type": "keyword",
      "text": [
        "luit :\n"
      ]
    },
    {
      "region_id": "r_10",
      "type": "keyword",
      "text": [
        "rubato :\n"
      ]
    },
    {
      "region_id": "r_12",
      "type": "keyword",
      "text": [
        "arpeggio :\n"
      ]
    },
    {
      "region_id": "r_14",
      "type": "keyword",
      "text": [
        "L. Couperin :\n"
      ]
    },
    {
      "region_id": "r_16",
      "type": "keyword",
      "text": [
        "Bassano :\n"
      ]
    },
    {
      "region_id": "r_19",
      "type": "keyword",
      "text": [
        "Gabrieli :\n"
      ]
    },
    {
      "region_id": "r_23",
      "type": "keyword",
      "text": [
        "diminutie :\n"
      ]
    },
    {
      "region_id": "r_25",
      "type": "keyword",
      "text": [
        "bassanello :\n"
      ]
    },
    {
      "region_id": "r_27",
      "type": "keyword",
      "text": [
        "Zarlino :\n"
      ]
    },
    {
      "region_id": "r_29",
      "type": "keyword",
      "text": [
        "Palestrina :\n"
      ]
    },
    {
      "region_id": "r_33",
      "type": "keyword",
      "text": [
        null
      ]
    },
    {
      "region_id": "r_35",
      "type": "keyword",
      "text": [
        "continuo :\n"
      ]
    },
    {
      "region_id": "r_39",
      "type": "keyword",
      "text": [
        "violone :\n"
      ]
    },
    {
      "region_id": "r_43",
      "type": "keyword",
      "text": [
        null
      ]
    },
    {
      "region_id": "r_45",
      "type": "keyword",
      "text": [
        "cello :\n"
      ]
    },
    {
      "region_id": "r_41",
      "type": "keyword",
      "text": [
        "blokfluit :\n"
      ]
    },
    {
      "region_id": "r_44",
      "type": "pages-keyword",
      "text": [
        "158"
      ]
    },
    {
      "region_id": "r_46",
      "type": "pages-keyword",
      "text": [
        "157, 158\n"
      ]
    },
    {
      "region_id": "r_49",
      "type": "keyword",
      "text": [
        "gitaar :\n"
      ]
    },
    {
      "region_id": "r_53",
      "type": "keyword",
      "text": [
        "riet :\n"
      ]
    },
    {
      "region_id": "r_55",
      "type": "keyword",
      "text": [
        "pochette :\n"
      ]
    },
    {
      "region_id": "r_47",
      "type": "keyword",
      "text": [
        "chitaronne francine :\n"
      ]
    },
    {
      "region_id": "r_51",
      "type": "keyword",
      "text": [
        "ad lib. bezetting :\n"
      ]
    },
    {
      "region_id": "r_54",
      "type": "pages-keyword",
      "text": [
        "173-182"
      ]
    },
    {
      "region_id": "r_56",
      "type": "pages-keyword",
      "text": [
        "185"
      ]
    },
    {
      "region_id": "r_621",
      "type": "shelfmark",
      "text": []
    },
    {
      "region_id": "r_37",
      "type": "keyword",
      "text": [
        "bezettig (instr)\n"
      ]
    },
    {
      "region_id": "r_40",
      "type": "pages-keyword",
      "text": [
        "156"
      ]
    },
    {
      "region_id": "r_42",
      "type": "pages-keyword",
      "text": [
        "158"
      ]
    },
    {
      "region_id": "r_31",
      "type": "keyword",
      "text": [
        "Monteverdi :\n"
      ]
    },
    {
      "region_id": "r_22",
      "type": "pages-keyword",
      "text": [
        "153"
      ]
    },
    {
      "region_id": "r_21",
      "type": "keyword",
      "text": [
        "zink :\n"
      ]
    },
    {
      "region_id": "r_4",
      "type": "pages-keyword",
      "text": [
        "132"
      ]
    },
    {
      "region_id": "r_8",
      "type": "pages-keyword",
      "text": [
        "134, 157\n"
      ]
    },
    {
      "region_id": "r_9",
      "type": "keyword",
      "text": [
        "preludes non mesuré :\n"
      ]
    },
    {
      "region_id": "r_11",
      "type": "pages-keyword",
      "text": [
        "145"
      ]
    },
    {
      "region_id": "r_13",
      "type": "pages-keyword",
      "text": [
        "146"
      ]
    },
    {
      "region_id": "r_17",
      "type": "pages-keyword",
      "text": [
        "153-158"
      ]
    },
    {
      "region_id": "r_20",
      "type": "pages-keyword",
      "text": [
        "153-158"
      ]
    },
    {
      "region_id": "r_24",
      "type": "pages-keyword",
      "text": [
        "153, 154\n"
      ]
    },
    {
      "region_id": "r_26",
      "type": "pages-keyword",
      "text": [
        "153"
      ]
    },
    {
      "region_id": "r_28",
      "type": "pages-keyword",
      "text": [
        "154"
      ]
    },
    {
      "region_id": "r_30",
      "type": "pages-keyword",
      "text": [
        "154"
      ]
    },
    {
      "region_id": "r_34",
      "type": "pages-keyword",
      "text": [
        "155"
      ]
    },
    {
      "region_id": "r_32",
      "type": "pages-keyword",
      "text": [
        "154, 155\n"
      ]
    },
    {
      "region_id": "r_36",
      "type": "pages-keyword",
      "text": [
        "155, 156, 157, 158\n"
      ]
    },
    {
      "region_id": "r_38",
      "type": "pages-keyword",
      "text": [
        "155, 156\n"
      ]
    },
    {
      "region_id": "r_50",
      "type": "pages-keyword",
      "text": [
        "184, 227, 229, 235, 237\n"
      ]
    },
    {
      "region_id": "r_52",
      "type": "pages-keyword",
      "text": [
        "167-172"
      ]
    },
    {
      "region_id": "r_48",
      "type": "pages-keyword",
      "text": [
        "164-166\n"
      ]
    },
    {
      "region_id": "r_15",
      "type": "pages-keyword",
      "text": [
        "143-152"
      ]
    },
    {
      "region_id": "r_18",
      "type": "pages-keyword",
      "text": [
        "143-153"
      ]
    },
    {
      "region_id": "r_6",
      "type": "pages-keyword",
      "text": [
        "132, 134, 156\n"
      ]
    },
    {
      "region_id": "r_2",
      "type": "pages-keyword",
      "text": [
        "127-142"
      ]
    }
  ],
  "relations": [
    {
      "type": "related_pages",
      "source": "r_27",
      "target": "r_28"
    },
    {
      "type": "related_pages",
      "source": "r_29",
      "target": "r_30"
    },
    {
      "type": "related_pages",
      "source": "r_31",
      "target": "r_32"
    },
    {
      "type": "related_pages",
      "source": "r_33",
      "target": "r_34"
    },
    {
      "type": "related_pages",
      "source": "r_37",
      "target": "r_38"
    },
    {
      "type": "related_pages",
      "source": "r_39",
      "target": "r_40"
    },
    {
      "type": "related_pages",
      "source": "r_41",
      "target": "r_42"
    },
    {
      "type": "related_pages",
      "source": "r_43",
      "target": "r_44"
    },
    {
      "type": "related_pages",
      "source": "r_45",
      "target": "r_46"
    },
    {
      "type": "related_pages",
      "source": "r_47",
      "target": "r_48"
    },
    {
      "type": "related_pages",
      "source": "r_49",
      "target": "r_50"
    },
    {
      "type": "related_pages",
      "source": "r_51",
      "target": "r_52"
    },
    {
      "type": "related_pages",
      "source": "r_53",
      "target": "r_54"
    },
    {
      "type": "related_pages",
      "source": "r_55",
      "target": "r_56"
    },
    {
      "type": "related_pages",
      "source": "r_35",
      "target": "r_36"
    },
    {
      "type": "related_pages",
      "source": "r_25",
      "target": "r_26"
    },
    {
      "type": "related_pages",
      "source": "r_23",
      "target": "r_24"
    },
    {
      "type": "related_pages",
      "source": "r_21",
      "target": "r_22"
    },
    {
      "type": "related_pages",
      "source": "r_19",
      "target": "r_20"
    },
    {
      "type": "related_pages",
      "source": "r_16",
      "target": "r_17"
    },
    {
      "type": "related_pages",
      "source": "r_14",
      "target": "r_15"
    },
    {
      "type": "related_pages",
      "source": "r_12",
      "target": "r_13"
    },
    {
      "type": "related_pages",
      "source": "r_10",
      "target": "r_11"
    },
    {
      "type": "related_pages",
      "source": "r_9",
      "target": "r_18"
    },
    {
      "type": "related_pages",
      "source": "r_7",
      "target": "r_8"
    },
    {
      "type": "related_pages",
      "source": "r_5",
      "target": "r_6"
    },
    {
      "type": "related_pages",
      "source": "r_3",
      "target": "r_4"
    },
    {
      "type": "related_pages",
      "source": "r",
      "target": "r_2"
    }
  ]
}